autofold/__init__.py
autofold/api.py
autofold/bot.py
autofold/database.py
autofold/strategy.py
autofold/subscriber.py
autofold/utils/__init__.py
autofold/utils/calculate_cpmm.py
autofold/utils/manifold_dump_reader.py
autofold/utils/str_utils.py
examples/__init__.py
examples/example_strategy.py
examples/test_install.py
autofold-0.2.1.dist-info/LICENSE.txt
autofold-0.2.1.dist-info/METADATA
autofold-0.2.1.dist-info/WHEEL
autofold-0.2.1.dist-info/top_level.txt
autofold-0.2.1.dist-info/RECORD
