Metadata-Version: 2.1
Name: autofold
Version: 0.2.1
Summary: Hassle-free and easy to use bot for [Manifold.markets](https://manifold.markets)
License: MIT License
Requires-Python: >=3.8
License-File: LICENSE.txt
Requires-Dist: toml
Requires-Dist: loguru
Requires-Dist: tinydb
Requires-Dist: apscheduler
Requires-Dist: requests
